README.rst
setup.py
torthrift/__init__.py
torthrift/client.py
torthrift/gen.py
torthrift/pool.py
torthrift.egg-info/PKG-INFO
torthrift.egg-info/SOURCES.txt
torthrift.egg-info/dependency_links.txt
torthrift.egg-info/requires.txt
torthrift.egg-info/top_level.txt
torthrift/server/__init__.py
torthrift/server/handler.py
torthrift/transport/__init__.py
torthrift/transport/stream.py
torthrift/transport/transport.py