Metadata-Version: 1.0
Name: torthrift
Version: 0.2.4
Summary: Tornado asynchronous thrift server and client
Home-page: http://github.com/snower/TorThrift
Author: snower
Author-email: sujian199@gmail.com
License: MIT
Platform: UNKNOWN
